revizor/__init__.py
revizor/model/char-bpe-model.pt
revizor/tagger.py
revizor/tokenizer.py
revizor/types.py
revizor/utils.py
revizor-0.2.0.dist-info/LICENSE
revizor-0.2.0.dist-info/WHEEL
revizor-0.2.0.dist-info/METADATA
revizor-0.2.0.dist-info/RECORD
