Metadata-Version: 2.1
Name: revizor
Version: 0.2.0
Summary: Ecommerce product title recognition package
Home-page: https://github.com/bureaucratic-labs/revizor
License: MIT
Keywords: natural language processing
Author: Dima Veselov
Author-email: d.a.veselov@yandex.ru
Requires-Python: >=3.8,<4.0
Classifier: Development Status :: 3 - Alpha
Classifier: Intended Audience :: Developers
Classifier: License :: OSI Approved :: MIT License
Classifier: Programming Language :: Python :: 3
Classifier: Programming Language :: Python :: 3.10
Classifier: Programming Language :: Python :: 3.8
Classifier: Programming Language :: Python :: 3.9
Classifier: Topic :: Scientific/Engineering :: Artificial Intelligence
Classifier: Topic :: Text Processing :: Linguistic
Requires-Dist: flair (>=0.8.0,<0.9.0)
Requires-Dist: razdel (>=0.5.0,<0.6.0)
Project-URL: Repository, https://github.com/bureaucratic-labs/revizor
